auth/__init__.py
auth/auth_functions.py
auth/jwt_functions.py
auth/middleware.py
fastapi_auth_core-0.1.2.dist-info/METADATA
fastapi_auth_core-0.1.2.dist-info/WHEEL
fastapi_auth_core-0.1.2.dist-info/RECORD
