Metadata-Version: 2.3
Name: fastapi-auth-core
Version: 0.1.2
Summary: Authentication core utilities including JWT token management.
License: MIT
Author: riya0865
Author-email: riya.dev0865@gmail.com
Requires-Python: >=3.13
Classifier: License :: OSI Approved :: MIT License
Classifier: Programming Language :: Python :: 3
Classifier: Programming Language :: Python :: 3.13
Requires-Dist: fastapi[standard] (>=0.115.12,<0.116.0)
Requires-Dist: passlib (>=1.7.4,<2.0.0)
Requires-Dist: pyjwt (>=2.10.1,<3.0.0)
